[
    {
        "start": 15.580000000000002,
        "end": 22.08,
        "text": " It's one of those unfortunate things, but bad things always happen to me"
    },
    {
        "start": 22.759999999999998,
        "end": 29.06,
        "text": " And you don't wanna keep the door open You wanted to see me fall out of motion"
    },
    {
        "start": 29.9,
        "end": 36.46,
        "text": " I ruined all my friendships with you And I think I'm running out of people to lose"
    },
    {
        "start": 37.1,
        "end": 43.34,
        "text": " I only have to give you my motion And you always find your way right back to me"
    },
    {
        "start": 43.34,
        "end": 48.7,
        "text": " This problem again, look what I started An A in your A"
    },
    {
        "start": 48.7,
        "end": 53.78,
        "text": " That's how it started A little bit more of this mystery"
    },
    {
        "start": 53.78,
        "end": 56.84,
        "text": " I will make you wish that you had never come to me"
    },
    {
        "start": 56.84,
        "end": 64.02,
        "text": " Cause I picture you one day after you improve And you're walking down the aisle, it's the thing that makes me smile"
    },
    {
        "start": 64.02,
        "end": 71.7,
        "text": " Keep me in bed, will you drive with me instead? No, you're not quite stuck with me, but one day you'll be"
    },
    {
        "start": 72.68,
        "end": 79.38,
        "text": " So why can't I be romantic with you? I'm guessing there's something about the stuff we went through"
    },
    {
        "start": 79.38,
        "end": 85.06,
        "text": " No, you'll never let me leave that behind us Leave it in California"
    },
    {
        "start": 87.24000000000001,
        "end": 93.56,
        "text": " This sticky situation with you Made me start booking all my tables for two"
    },
    {
        "start": 94.35999999999999,
        "end": 100.62,
        "text": " I still refer to you as an option Cause you always find your way right back to me"
    },
    {
        "start": 100.62,
        "end": 106.0,
        "text": " This problem again, look what I started An A in your A"
    },
    {
        "start": 106.0,
        "end": 111.08,
        "text": " That's how it started A little bit more of this mystery"
    },
    {
        "start": 111.08,
        "end": 114.16,
        "text": " I will make you wish that you had never come to me"
    },
    {
        "start": 114.16,
        "end": 121.42,
        "text": " Cause I picture you one day after you improve And you're walking down the aisle, it's the thing that makes me smile"
    },
    {
        "start": 121.42,
        "end": 128.9,
        "text": " Keep me in bed, will you drive with me instead? No, you're not quite stuck with me, but one day you'll be"
    },
    {
        "start": 128.9,
        "end": 135.88,
        "text": " You can say you're sorry, do you ever really mean it? You and your Ferrari might just make you seem appealing"
    },
    {
        "start": 135.88,
        "end": 143.34,
        "text": " Looking at your photos, when did your life get so quiet? Open up your doors to me and I'll enter inside it"
    },
    {
        "start": 164.38,
        "end": 165.78,
        "text": " Thanks for watching!"
    }
]